hubify/__init__.py
hubify/defaults.py
hubify/plot.py
hubify/transformations.py
hubify-0.3.0.dist-info/WHEEL
hubify-0.3.0.dist-info/METADATA
hubify-0.3.0.dist-info/RECORD
